smartlingApiSdk/ApiResponse.py
smartlingApiSdk/ApiV2.py
smartlingApiSdk/AuthClient.py
smartlingApiSdk/Constants.py
smartlingApiSdk/Credentials.py
smartlingApiSdk/FileApiBase.py
smartlingApiSdk/FileApiV2.py
smartlingApiSdk/HttpClient.py
smartlingApiSdk/Logger.py
smartlingApiSdk/MultipartPostHandler.py
smartlingApiSdk/ObsoleteApiV1.py
smartlingApiSdk/ObsoleteSmartlingFileApi.py
smartlingApiSdk/ProjectsApiV2.py
smartlingApiSdk/ProxySettings.py
smartlingApiSdk/Settings.py
smartlingApiSdk/SmartlingDirective.py
smartlingApiSdk/SmartlingFileApiV2.py
smartlingApiSdk/SmartlingProjectsApiV2.py
smartlingApiSdk/UploadData.py
smartlingApiSdk/UrlV2Helper.py
smartlingApiSdk/__init__.py
smartlingApiSdk/version.py
smartlingApiSdk/api/AccountProjectsApi.py
smartlingApiSdk/api/ContextApi.py
smartlingApiSdk/api/EstimatesApi.py
smartlingApiSdk/api/FilesApi.py
smartlingApiSdk/api/JobBatchesV2Api.py
smartlingApiSdk/api/JobsApi.py
smartlingApiSdk/api/StringsApi.py
smartlingApiSdk/api/TagsApi.py
smartlingApiSdk/api/__init__.py
smartlingApiSdk/api/patch_nose.py
smartlingApiSdk/example/AccountProjectsExample.py
smartlingApiSdk/example/ContextExample.py
smartlingApiSdk/example/EstimatesExample.py
smartlingApiSdk/example/FilesExample.py
smartlingApiSdk/example/FilesSimpleExample.py
smartlingApiSdk/example/JobBatchesV2Example.py
smartlingApiSdk/example/JobsExample.py
smartlingApiSdk/example/MultipleAccountsExample.py
smartlingApiSdk/example/MultipleProjectsExample.py
smartlingApiSdk/example/StringsExample.py
smartlingApiSdk/example/TagsExample.py
smartlingApiSdk/example/__init__.py
smartlingApiSdk/resources/ctx_api_test.png
smartlingApiSdk/resources/java.properties
smartlingApiSdk/resources/javaUTF16.properties
smartlingApiSdk/resources/test.csv
smartlingApiSdk/resources/test_import.xml
smartlingApiSdk/resources/test_import_es.xml
SmartlingApiSdk-3.1.9.dist-info/METADATA
SmartlingApiSdk-3.1.9.dist-info/WHEEL
SmartlingApiSdk-3.1.9.dist-info/top_level.txt
SmartlingApiSdk-3.1.9.dist-info/RECORD
