Metadata-Version: 2.1
Name: SmartlingApiSdk
Version: 3.1.9
Summary: python library to work with Smartling translation services APIs
Home-page: 
Author: Smartling, Inc.
Author-email: aartamonov@smartling.com
License: Apache License v2.0
Keywords: translation localization internationalization
